understanding_machine/__init__.py
understanding_machine-0.0.1.dist-info/licenses/LICENSE
understanding_machine-0.0.1.dist-info/METADATA
understanding_machine-0.0.1.dist-info/WHEEL
understanding_machine-0.0.1.dist-info/top_level.txt
understanding_machine-0.0.1.dist-info/RECORD
