Metadata-Version: 2.4
Name: understanding-machine
Version: 0.0.1
Summary: A Machine that understands
Author-email: Alexander Fedotov <alex.fedotov@aol.com>
Project-URL: Homepage, https://github.com/understanding-machine/understanding-machine
Project-URL: Bug Tracker, https://github.com/understanding-machine/understanding-machine/issues
Classifier: Programming Language :: Python :: 3
Classifier: License :: OSI Approved :: MIT License
Classifier: Operating System :: OS Independent
Requires-Python: >=3.10
License-File: LICENSE
Dynamic: license-file
